{
  "products": {
    "traditional_cakes": [
      {
        "id": 1,
        "name": "Pastel de chocolate",
        "image": "https://donamaria.com.br/wp-content/uploads/2020/10/119667634_2752204955067886_7739037335102047089_o.jpg",
        "desc": "Delicioso pastel con suave masa de chocolate y ganache de chocolate oscuro.",
        "price": 8.85,
        "cat": "traditional cake"
      },
      {
        "id": 2,
        "name": "Pastel de cumpleaños",
        "image": "https://wiltonenespanol.com/wp-content/uploads/2020/11/Sprinkle-on-the-Fun-Birthday-Cake.jpg",
        "desc": "Sabores clásicos e innovadores para tu cumpleaños.",
        "price": 11.95,
        "cat": "traditional cake"
      },
      {
        "id": 3,
        "name": "Pastel de 3 leches",
        "image": "https://www.recetasderechupete.com/wp-content/uploads/2020/11/Pastel-tres-leches-portada-2-scaled.jpg",
        "desc": "Combinación de texturas y sabores con tres tipos de leche.",
        "price": 11,
        "cat": "traditional cake"
      },
      {
        "id": 4,
        "name": "Pastel de fresa",
        "image": "https://d1kxxrc2vqy8oa.cloudfront.net/wp-content/uploads/2019/08/15111756/RFB-0708-3-tortadefresas.jpg",
        "desc": "Base rellena con mermelada de fresa fresca y crema de queso.",
        "price": 10.25,
        "cat": "traditional cake"
      },
      {
        "id": 5,
        "name": "Pastel de melocotón",
        "image": "https://www.pasteleite.com/wp-content/uploads/2020/05/torta-de-duraznos.jpg",
        "desc": "Base rellena con trozos jugosos de melocotón y crema batida.",
        "price": 10.30,
        "cat": "traditional cake"
      },
      {
        "id": 6,
        "name": "Pastel de quinceañera",
        "image": "https://www.pastelescisnecakesandpastriescolorado.com/wp-content/gallery/quince-anos/Pastel-de-Quinceanera-en-Denver-CO-Pasteles-Cisne-4.jpeg",
        "desc": "Decorado con elegancia y relleno de crema de vainilla y fresas frescas.",
        "price": 25.50,
        "cat": "traditional cake"
      },
      {
        "id": 7,
        "name": "Pastel de caramelo",
        "image": "https://assets.elgourmet.com/wp-content/uploads/2023/03/cover_p1hugt36ex_salado-1024x683.jpg.webp",
        "desc": "Textura y sabor a caramelo con toque de palomitas de maíz.",
        "price": 14.60,
        "cat": "traditional cake"
      },
      {
        "id": 8,
        "name": "Pastel de coco",
        "image": "https://images.hola.com/imagenes/cocina/recetas/20230208226055/tarta-coco-merengue/1-201-364/tarta-coco-age-t.jpg",
        "desc": "Cubierto por fondant de vainilla y relleno de coco.",
        "price": 11.30,
        "cat": "traditional cake"
      },
      {
        "id": 9,
        "name": "Pastel de baby shower",
        "image": "https://tutusparafiestas.com/wp-content/uploads/2016/04/Pasteles-para-baby-shower-de-ni%C3%B1o-20.jpg",
        "desc": "Sabores únicos y decoraciones únicas para celebrar la llegada del nuevo miembro de la familia.",
        "price": 18.55,
        "cat": "traditional cake"
      },
      {
        "id": 10,
        "name": "Pastel de bodas",
        "image": "https://cdn0.matrimonio.com.co/article/9533/3_2/1280/jpg/3359-pastel-adornado-con-flores.jpeg",
        "desc": "Elegante y exquisito, decorado a tu gusto y relleno de capas de bizcocho húmedo y cremosa mousse de vainilla y frutas frescas.",
        "price": 25.70,
        "cat": "traditional cake"
      }
    ],
    "thematic_cakes": [
      {
        "id": 11,
        "name": "Temático Halloween",
        "image": "https://i.pinimg.com/736x/82/ee/d9/82eed91b2ac802e1c564f811d15943eb.jpg",
        "desc": "Pastel de bizcocho de chocolate y frosting de vainilla.",
        "price": 15,
        "cat": "thematic cake"
      },
      {
        "id": 12,
        "name": "Temático Dinosaurios",
        "image": "https://minilook.com.ar/wp-content/uploads/2021/01/torta-de-dinosaurios-para-ninos-grandes.jpg",
        "desc": "Pastel de aventura prehistórica decorado con fondant.",
        "price": 22.10,
        "cat": "thematic cake"
      },
      {
        "id": 13,
        "name": "Temático Gatitos",
        "image": "https://i.pinimg.com/originals/fc/41/50/fc41506bbffa609c727bcff550e477c0.jpg",
        "desc": "Pastel de gatitos con bizcocho de vainilla y fondant de queso.",
        "price": 16.85,
        "cat": "thematic cake"
      },
      {
        "id": 14,
        "name": "Temático Playa",
        "image": "https://i.pinimg.com/originals/27/aa/0a/27aa0a2ac54918e595264dd87190f90c.jpg",
        "desc": "Pastel refrescante de verano cubierto de fondant de coco y adornado con detalles de playa.",
        "price": 23.46,
        "cat": "thematic cake"
      },
      {
        "id": 15,
        "name": "Temático Espacio",
        "image": "https://i.pinimg.com/originals/c3/d4/3c/c3d43c9004cbb77d7bbbec51b1a39414.png",
        "desc": "Textura y decoración cósmica que te transportarán al espacio.",
        "price": 20.33,
        "cat": "thematic cake"
      },
      {
        "id": 16,
        "name": "Temático Girasoles",
        "image": "https://brigams.pe/wp-content/uploads/GIRASOL-FRONTAL-scaled.jpg",
        "desc": "Pastel de girasoles con capas de bizcocho y crema de girasol.",
        "price": 17.20,
        "cat": "thematic cake"
      },
      {
        "id": 17,
        "name": "Temático Acuático",
        "image": "https://i.pinimg.com/236x/f8/9b/a9/f89ba928589964b1ced12f539847bfe1--sea-cakes-fancy-cakes.jpg",
        "desc": "Pastel acuático decorado con criaturas marinas en fondant y relleno de cremoso chocolate.",
        "price": 13.05,
        "cat": "thematic cake"
      },
      {
        "id": 18,
        "name": "Temático Retro",
        "image": "https://i.pinimg.com/originals/1b/a6/86/1ba686c1021f640267047ec5c584a83e.jpg",
        "desc": "Pastel retro con capas de bizcocho de vainilla y crema de mantequilla de fresa.",
        "price": 20.21,
        "cat": "thematic cake"
      },
      {
        "id": 19,
        "name": "Temático Gamer",
        "image": "https://pbs.twimg.com/media/FAOcsGNUYAI7us3.jpg:large",
        "desc": "Pastel gamer decorado con detalles en fondant de iconos de videojuegos y relleno de crema de chocolate y fresa.",
        "price": 19.90,
        "cat": "thematic cake"
      },
      {
        "id": 20,
        "name": "Temático CETD",
        "image": "https://i.pinimg.com/736x/3d/b2/82/3db2820546b3ebbcdc7de85b5c3add71.jpg",
        "desc": "Pastel de Cómo Entrenar a Tu Dragón con decoración en fondant de Hippo y Chimuelo.",
        "price": 15.30,
        "cat": "thematic cake"
      }
    ],
    "customized_cakes": [
      {
        "id": 21,
        "name": "Personalizado Naruto",
        "image": "https://i.pinimg.com/originals/54/82/bd/5482bd41d1a5c2543dc772d3ab4fe4dd.jpg",
        "desc": "Pastel de Naruto con bizcocho de vainilla y cobertura de chocolate.",
        "price": 19.90,
        "cat": "customized cake"
      },
      {
        "id": 22,
        "name": "Personalizado Minecraft",
        "image": "https://aranzazu.com/wp-content/uploads/2023/03/producto-web-base-especiales-dia-del-ninocopia-copia.webp",
        "desc": "Pastel temático de Creeper con bizcocho de vainilla y fondant verde.",
        "price": 20.10,
        "cat": "customized cake"
      },
      {
        "id": 23,
        "name": "Personalizado Beastars",
        "image": "https://pbs.twimg.com/media/Elk3u_qU4AMnejM.jpg",
        "desc": "Pastel de vainilla con glaseado de turrón y decoración de personajes de anime.",
        "price": 14.35,
        "cat": "customized cake"
      },
      {
        "id": 24,
        "name": "Personalizado Barbie",
        "image": "https://d2r9epyceweg5n.cloudfront.net/stores/002/197/435/products/barbie-2-pisos1-3cbaea94d8ccd5bd0f16737279429900-1024-1024.webp",
        "desc": "Pastel con textura suave y cubierta de fondant blanca con turrón rosado.",
        "price": 21.35,
        "cat": "customized cake"
      },
      {
        "id": 25,
        "name": "Personalizado Ladybug",
        "image": "https://pm1.narvii.com/6552/b7bd6bb90fa08c4e5db89422de742075ce8b8a38_hq.jpg",
        "desc": "Pastel de Ladybug y Cat Noir decorado con diseños de héroes de París.",
        "price": 21.40,
        "cat": "customized cake"
      },
      {
        "id": 26,
        "name": "Personalizado Melody",
        "image": "https://pbs.twimg.com/media/FWsebP_WIAEw3KV.jpg",
        "desc": "Pastel de My Melody para momentos tiernos y dulces.",
        "price": 15.50,
        "cat": "customized cake"
      },
      {
        "id": 27,
        "name": "Personalizado HP",
        "image": "https://elcomercio.pe/resizer/2QzHIUMSIJ_09iQ8xEV7ry85Pyo=/1200x800/smart/filters:format(jpeg):quality(75)/cloudfront-us-east-1.images.arcpublishing.com/elcomercio/SYZV2D2ARJFSRLO2QKE5SAV7UM.jpg",
        "desc": "Pastel inspirado en Harry Potter para fiestas mágicas.",
        "price": 15,
        "cat": "customized cake"
      },
      {
        "id": 28,
        "name": "Personalizado Shrek",
        "image": "https://i.pinimg.com/736x/9f/cd/a7/9fcda7897996f342a02b8aedac595081.jpg",
        "desc": "El pastel más delicioso y divertido que hayas probado.",
        "price": 18.65,
        "cat": "customized cake"
      },
      {
        "id": 29,
        "name": "Personalizado Cars",
        "image": "https://i.pinimg.com/originals/16/0e/dd/160edd4d188ca6dba3adffcf42045eee.jpg",
        "desc": "Pastel de fresa con mermelada de fresa fresca y crema de queso.",
        "price": 15.30,
        "cat": "customized cake"
      },
      {
        "id": 30,
        "name": "Personalizado Fútbol",
        "image": "https://media.istockphoto.com/id/1058558528/es/foto/anivers%C3%A1rio-de-bolo.jpg?s=612x612&w=0&k=20&c=8vKssMfyaSrDCv10du16R8782TjsmTQJA605NeIMeyA=",
        "desc": "Pastel futbolista con masa deliciosa y decoración de verde-blanco.",
        "price": 10,
        "cat": "customized cake"
      }
    ]
  }
}